twiz/__init__.py
twiz/extract.py
twiz/main.py
twiz/parser.py
twiz/model/__init__.py
twiz/model/account.py
twiz/model/follower.py
twiz/model/following.py
twiz/model/like.py
twiz/model/manip.py
twiz/model/ad/__init__.py
twiz/model/ad/engagement/__init__.py
twiz/model/ad/engagement/advertiser.py
twiz/model/ad/engagement/attributes.py
twiz/model/ad/engagement/criteria.py
twiz/model/ad/engagement/device.py
twiz/model/ad/engagement/engagement.py
twiz/model/ad/engagement/engagements.py
twiz/model/ad/engagement/tweet.py
twiz/model/tweet/__init__.py
twiz/model/tweet/mention.py
twiz/model/tweet/tweet.py
twiz/model/tweet/tweets.py
twiz/model/tweet/url.py
twiz/plot/__init__.py
twiz/plot/util.py
twiz/plot/ad/__init__.py
twiz/plot/ad/engagement/__init__.py
twiz/plot/ad/engagement/viz.py
twiz/plot/tweet/__init__.py
twiz/plot/tweet/viz.py
twiz-0.3.4.dist-info/entry_points.txt
twiz-0.3.4.dist-info/LICENSE
twiz-0.3.4.dist-info/WHEEL
twiz-0.3.4.dist-info/METADATA
twiz-0.3.4.dist-info/RECORD
