Metadata-Version: 2.1
Name: twiz
Version: 0.3.4
Summary: twiz - Your Twitter Account Data Analysis & Visualization Tool <3
Home-page: https://itzmeanjan.github.io/twiz
License: UNKNOWN
Author: Anjan Roy
Author-email: anjanroy@yandex.com
Requires-Python: >=3.7
Classifier: Intended Audience :: End Users/Desktop
Classifier: Programming Language :: Python :: 3
Requires-Dist: matplotlib
Requires-Dist: seaborn
Requires-Dist: emoji
Requires-Dist: wordcloud
Requires-Dist: dataclasses
Requires-Dist: python_dateutil
Requires-Dist: flit ; extra == "dev"
Provides-Extra: dev
